pingkit/__init__.py
pingkit/embedding.py
pingkit/extraction.py
pingkit/generate.py
pingkit/model.py
pingkit-0.4.9.dist-info/licenses/LICENSE
pingkit-0.4.9.dist-info/METADATA
pingkit-0.4.9.dist-info/WHEEL
pingkit-0.4.9.dist-info/entry_points.txt
pingkit-0.4.9.dist-info/top_level.txt
pingkit-0.4.9.dist-info/RECORD
