Metadata-Version: 2.4
Name: pingkit
Version: 0.4.9
Summary: LLM classification toolkit
Author-email: Jacob Berkowitz <jacob.berkowitz2@cshs.org>
License-Expression: MIT
Requires-Python: >=3.8
License-File: LICENSE
Requires-Dist: torch>=2.2
Requires-Dist: torchvision
Requires-Dist: transformers>=4.40
Requires-Dist: pandas>=1.1
Requires-Dist: numpy>=1.20
Requires-Dist: scikit-learn>=1.0
Requires-Dist: joblib>=1.2
Requires-Dist: tqdm>=4.60
Requires-Dist: matplotlib>=3.4
Requires-Dist: rich>=13.0
Requires-Dist: typer[all]>=0.9
Dynamic: license-file
